{
  "version": 3,
  "common": {
    "console": {
      "enabled": true,
      "host": "0.0.0.0",
      "port": 18765,
      "auto_open_browser": true,
      "open_browser_delay_sec": 1,
      "ui_theme": "light",
      "log_buffer_size": 5000,
      "enable_sse": true
    },
    "deployment": {
      "role_mode": "internal",
      "last_started_role_mode": "internal",
      "node_id": "",
      "node_label": "内网端"
    },
    "internal_bridge_http": {
      "enabled": true,
      "bind_host": "0.0.0.0",
      "port": 18765,
      "base_url": "http://172.16.1.2:18765",
      "auth_token": "",
      "allowed_client_ips": [
        "172.16.1.1"
      ],
      "connect_timeout_sec": 3,
      "read_timeout_sec": 15,
      "request_timeout_sec": 15,
      "max_attempts": 2
    },
    "paths": {
      "business_root_dir": "D:\\QLDownload",
      "runtime_state_root": ".runtime"
    },
    "internal_source_sites": [
      {
        "building": "A楼",
        "enabled": true,
        "host": "192.168.210.50",
        "username": "admin",
        "password": "BMS@123456",
        "url": null
      },
      {
        "building": "B楼",
        "enabled": true,
        "host": "192.168.220.50",
        "username": "admin",
        "password": "BMS123456",
        "url": null
      },
      {
        "building": "C楼",
        "enabled": true,
        "host": "192.168.231.53",
        "username": "admin",
        "password": "BMS@123456",
        "url": null
      },
      {
        "building": "D楼",
        "enabled": true,
        "host": "192.168.232.53",
        "username": "admin",
        "password": "123456",
        "url": null
      },
      {
        "building": "E楼",
        "enabled": true,
        "host": "192.168.233.57",
        "username": "admin",
        "password": "BMS@123456",
        "url": null
      }
    ],
    "internal_source_cache": {
      "enabled": true,
      "run_on_startup": true,
      "check_interval_sec": 30,
      "hour_bucket_mode": "natural_hour",
      "latest_required": true,
      "history_fill_timeout_sec": 1800,
      "monthly_report_download": {
        "enabled": true,
        "run_time": "01:00:00",
        "retry_interval_sec": 300
      },
      "top5_monthly_report_download": {
        "enabled": true,
        "day_of_month": 2,
        "run_time": "02:00:00",
        "retry_interval_sec": 300
      },
      "daily_source_download": {
        "enabled": true,
        "run_time": "00:30:00",
        "retry_interval_sec": 300,
        "families": [
          "branch_power_family",
          "branch_current_family",
          "branch_switch_family",
          "building_full_cabinet_power_family",
          "air_conditioner_temperature_humidity_family"
        ]
      }
    },
    "shared_bridge": {
      "enabled": true,
      "root_dir": "D:\\share",
      "internal_root_dir": "D:\\share",
      "poll_interval_sec": 2,
      "heartbeat_interval_sec": 5,
      "claim_lease_sec": 30,
      "stale_task_timeout_sec": 1800,
      "artifact_retention_days": 7,
      "sqlite_busy_timeout_ms": 15000
    },
    "feishu_auth": {}
  }
}
